kt/__init__.py
kt/testing/__init__.py
kt/testing/cleanup.py
kt/testing/requests.py
kt/testing/tests/__init__.py
kt/testing/tests/cleanup.py
kt/testing/tests/composite.py
kt/testing/tests/requests.py
kt.testing-3.1.2.dist-info/LICENSE.rst
kt.testing-3.1.2.dist-info/METADATA
kt.testing-3.1.2.dist-info/WHEEL
kt.testing-3.1.2.dist-info/top_level.txt
kt.testing-3.1.2.dist-info/RECORD
