Metadata-Version: 2.1
Name: kt.testing
Version: 3.1.2
Summary: Test support code featuring flexible harness composition
Home-page: https://github.com/keepertech/kt.testing
Author: Fred L. Drake, Jr.
Author-email: fred@fdrake.net
License: UNKNOWN
Platform: UNKNOWN
Classifier: Intended Audience :: Developers
Classifier: License :: OSI Approved :: BSD License
Classifier: Programming Language :: Python :: 2.7
Classifier: Programming Language :: Python :: 3.4
Classifier: Programming Language :: Python :: 3.5
Classifier: Programming Language :: Python :: 3.6
Classifier: Programming Language :: Python :: 3.7
Classifier: Topic :: Software Development :: Testing
Requires-Dist: requests
Requires-Dist: six
Provides-Extra: test
Requires-Dist: nose ; extra == 'test'
